linty_fresh/__init__.py
linty_fresh/main.py
linty_fresh/problem.py
linty_fresh/linters/__init__.py
linty_fresh/linters/android.py
linty_fresh/linters/buck_unittest.py
linty_fresh/linters/checkstyle.py
linty_fresh/linters/mypy.py
linty_fresh/linters/passthrough.py
linty_fresh/linters/pmd.py
linty_fresh/linters/pylint.py
linty_fresh/linters/swiftlint.py
linty_fresh/linters/xcodebuild.py
linty_fresh/reporters/__init__.py
linty_fresh/reporters/github_reporter.py
linty_fresh/storage/__init__.py
linty_fresh/storage/git_storage_engine.py
linty_fresh-0.7.0.dist-info/METADATA
linty_fresh-0.7.0.dist-info/RECORD
linty_fresh-0.7.0.dist-info/WHEEL
linty_fresh-0.7.0.dist-info/entry_points.txt
linty_fresh-0.7.0.dist-info/top_level.txt
