Metadata-Version: 2.1
Name: linty-fresh
Version: 0.7.0
Summary: 
Home-page: https://github.com/lyft/linty_fresh
Author: Roy Williams
Author-email: rwilliams@lyft.com
License: apache
Platform: UNKNOWN
Classifier: Environment :: Console
Classifier: Intended Audience :: Developers
Classifier: License :: OSI Approved :: Apache Software License
Classifier: Programming Language :: Python
Classifier: Programming Language :: Python :: 3
Classifier: Topic :: Software Development :: Quality Assurance
Requires-Dist: aiohttp (<3.0.0,>=0.19.0)
Requires-Dist: typing (<4.0.0,>=3.5.0.1)
